Metadata-Version: 2.1
Name: dmpuser
Version: 1.39.85
Summary: fake:)
Home-page: UNKNOWN
Author-email: adamisaev92341@gmail.com
License: UNKNOWN
Platform: UNKNOWN
